examplenewproject/__init__.py
examplenewproject/examplenewproject.cpython-311-darwin.so
examplenewproject/wrapper.py
examplenewproject-0.3.dist-info/LICENSE
examplenewproject-0.3.dist-info/METADATA
examplenewproject-0.3.dist-info/WHEEL
examplenewproject-0.3.dist-info/top_level.txt
examplenewproject-0.3.dist-info/RECORD
