Metadata-Version: 2.1
Name: examplenewproject
Version: 0.3
Summary: A Python wrapper for a C++ project
Home-page: https://github.com/brainvs/examplenewproject
Author: Vasfi Tataroglu
Author-email: testestteestetestes2009@gmail.com
Classifier: Programming Language :: Python :: 3
Classifier: License :: OSI Approved :: MIT License
Classifier: Operating System :: OS Independent
Requires-Python: >=3.6
License-File: LICENSE
